math_engine/AST_Node_Types.py
math_engine/ScientificEngine.py
math_engine/__init__.py
math_engine/calculator.py
math_engine/cli.py
math_engine/config.json
math_engine/config_manager.py
math_engine/error.py
math_engine/non_decimal_utility.py
math_engine/utility.py
math_engine-0.5.0.dist-info/LICENSE
math_engine-0.5.0.dist-info/METADATA
math_engine-0.5.0.dist-info/WHEEL
math_engine-0.5.0.dist-info/entry_points.txt
math_engine-0.5.0.dist-info/top_level.txt
math_engine-0.5.0.dist-info/RECORD
