Metadata-Version: 2.1
Name: math-engine
Version: 0.5.0
Summary: A fast and secure mathematical expression evaluator.
Author-email: Jan Teske <jan.teske.06@gmail.com>
Project-URL: Homepage, https://github.com/JanTeske06/math_engine
Project-URL: Source, https://github.com/JanTeske06/math_engine
Project-URL: Changelog, https://github.com/JanTeske06/math_engine/blob/master/CHANGELOG.md
Classifier: Programming Language :: Python :: 3
Classifier: License :: OSI Approved :: MIT License
Classifier: Operating System :: OS Independent
Requires-Python: >=3.8
License-File: LICENSE
